[{"amount":1,"color":"#d6f7b3"},{"amount":1,"color":"#7bf1be"},{"amount":1,"color":"#64faaa"},{"amount":1,"color":"#b550f4"},{"amount":1,"color":"#acfbfc"},{"amount":1,"color":"#7ae2f8"},{"amount":1,"color":"#9ed5fc"},{"amount":1,"color":"#fc71cf"},{"amount":1,"color":"#7ec6f7"},{"amount":1,"color":"#ec4caa"},{"amount":1,"color":"#faf875"},{"amount":1,"color":"#f09ce1"},{"amount":1,"color":"#e7b9fc"},{"amount":1,"color":"#ecfeca"},{"amount":1,"color":"#f6738d"},{"amount":1,"color":"#ecb8f4"},{"amount":1,"color":"#c8fbb9"},{"amount":1,"color":"#c8dcf6"},{"amount":1,"color":"#f8eed2"},{"amount":1,"color":"#f8eac9"},{"amount":1,"color":"#c9f66e"},{"amount":1,"color":"#f5f5bc"},{"amount":1,"color":"#bef9da"},{"amount":1,"color":"#a8f6a4"},{"amount":1,"color":"#bd8eff"},{"amount":1,"color":"#f3e6a0"},{"amount":1,"color":"#e7d06b"},{"amount":1,"color":"#68ff44"},{"amount":1,"color":"#b0f19d"},{"amount":1,"color":"#dcfa82"},{"amount":1,"color":"#f174db"},{"amount":1,"color":"#def0a7"},{"amount":1,"color":"#abf3fa"},{"amount":1,"color":"#f7ad4f"},{"amount":1,"color":"#b7bbf3"},{"amount":1,"color":"#6ef691"},{"amount":1,"color":"#82f4d8"},{"amount":1,"color":"#f4ed95"},{"amount":1,"color":"#7e5cf2"},{"amount":1,"color":"#9bf6f4"},{"amount":1,"color":"#ddf5aa"},{"amount":1,"color":"#9769fc"},{"amount":1,"color":"#e84c5f"},{"amount":1,"color":"#f58842"},{"amount":1,"color":"#8ae671"},{"amount":1,"color":"#f8c9da"},{"amount":1,"color":"#ad72ec"},{"amount":1,"color":"#cff291"},{"amount":1,"color":"#51fb74"},{"amount":1,"color":"#c2fee5"},{"amount":1,"color":"#43faed"},{"amount":1,"color":"#9a80f3"},{"amount":1,"color":"#fc5095"},{"amount":1,"color":"#acf6b7"},{"amount":1,"color":"#f1cca8"},{"amount":1,"color":"#eeaa64"},{"amount":1,"color":"#de56ed"},{"amount":1,"color":"#9ff882"},{"amount":1,"color":"#b4c6fa"},{"amount":1,"color":"#bdfc9a"},{"amount":1,"color":"#67fda3"},{"amount":1,"color":"#3fb7f8"},{"amount":1,"color":"#b2c5f2"},{"amount":1,"color":"#f7b7d7"},{"amount":1,"color":"#f19899"},{"amount":1,"color":"#7febb6"},{"amount":1,"color":"#9df8a8"},{"amount":1,"color":"#38fc75"},{"amount":1,"color":"#f4a795"},{"amount":1,"color":"#f9b6b2"},{"amount":1,"color":"#50faf8"},{"amount":1,"color":"#eebd81"},{"amount":1,"color":"#b1f149"},{"amount":1,"color":"#f3aa7b"},{"amount":1,"color":"#8afed7"},{"amount":1,"color":"#a3efb7"},{"amount":1,"color":"#facfac"},{"amount":1,"color":"#f67e96"},{"amount":1,"color":"#c1adf6"},{"amount":1,"color":"#d5a8f5"},{"amount":1,"color":"#fadaa6"},{"amount":1,"color":"#f58c6e"},{"amount":1,"color":"#f9fa88"},{"amount":1,"color":"#48f657"},{"amount":1,"color":"#b1d8f3"},{"amount":1,"color":"#f3fbae"},{"amount":1,"color":"#d3f199"},{"amount":1,"color":"#6cf788"},{"amount":1,"color":"#bbf5a9"},{"amount":1,"color":"#d3f8b3"},{"amount":1,"color":"#d2f9ec"},{"amount":1,"color":"#d2fac4"},{"amount":1,"color":"#d1f74f"},{"amount":1,"color":"#3c36fc"},{"amount":1,"color":"#fc8bd8"},{"amount":1,"color":"#76e6f1"},{"amount":1,"color":"#9cfab5"},{"amount":1,"color":"#f7ecac"},{"amount":1,"color":"#fb377f"},{"amount":1,"color":"#86f7e9"},{"amount":1,"color":"#f18d45"},{"amount":1,"color":"#beaff4"},{"amount":1,"color":"#5f76fc"},{"amount":1,"color":"#b954fc"},{"amount":1,"color":"#e96652"},{"amount":1,"color":"#f7ee88"},{"amount":1,"color":"#a1f7df"},{"amount":1,"color":"#f98bef"},{"amount":1,"color":"#6ceca6"},{"amount":1,"color":"#ef9361"},{"amount":1,"color":"#5be5a8"},{"amount":1,"color":"#d6f993"},{"amount":1,"color":"#f7d0c4"},{"amount":1,"color":"#f8efac"},{"amount":1,"color":"#f6fe7d"},{"amount":1,"color":"#71dbfa"},{"amount":1,"color":"#eeb79c"},{"amount":1,"color":"#e89659"},{"amount":1,"color":"#e6fb91"},{"amount":1,"color":"#885af0"},{"amount":1,"color":"#94fa4c"},{"amount":1,"color":"#aff172"},{"amount":1,"color":"#b4f3c5"},{"amount":1,"color":"#8189f7"},{"amount":1,"color":"#90e465"},{"amount":1,"color":"#4d4cf5"},{"amount":1,"color":"#91f9ac"},{"amount":1,"color":"#d9fbbe"},{"amount":1,"color":"#ea614a"},{"amount":1,"color":"#f0f7ad"},{"amount":1,"color":"#7e64fc"},{"amount":1,"color":"#f1e9a8"},{"amount":1,"color":"#4377fc"},{"amount":1,"color":"#cb7ff2"},{"amount":1,"color":"#facdfe"},{"amount":1,"color":"#5bede6"},{"amount":1,"color":"#e98b74"},{"amount":1,"color":"#fc9efb"},{"amount":1,"color":"#e3fb80"},{"amount":1,"color":"#9652f6"},{"amount":1,"color":"#f8aff5"},{"amount":1,"color":"#a697f2"},{"amount":1,"color":"#ee8aee"},{"amount":1,"color":"#beffc7"},{"amount":1,"color":"#b4abfd"},{"amount":1,"color":"#f9d8a2"},{"amount":1,"color":"#f78a5d"},{"amount":1,"color":"#febdc8"},{"amount":1,"color":"#82ecc4"},{"amount":1,"color":"#b1ddf2"},{"amount":1,"color":"#e86bce"},{"amount":1,"color":"#89e64f"},{"amount":1,"color":"#ae41fe"},{"amount":1,"color":"#f595b0"},{"amount":1,"color":"#fee46e"},{"amount":1,"color":"#fea6e5"},{"amount":1,"color":"#f5ab58"},{"amount":1,"color":"#f6dd89"},{"amount":1,"color":"#7f71f5"},{"amount":1,"color":"#c9e0fd"},{"amount":1,"color":"#f64bb7"},{"amount":1,"color":"#f2f166"},{"amount":1,"color":"#92d9fe"},{"amount":1,"color":"#c1f9a7"},{"amount":1,"color":"#92f081"},{"amount":1,"color":"#fc5e48"},{"amount":1,"color":"#73ef8c"},{"amount":1,"color":"#9ea7f8"},{"amount":1,"color":"#54f445"},{"amount":1,"color":"#5ef993"},{"amount":1,"color":"#c9ef9d"},{"amount":1,"color":"#e3a1fd"},{"amount":1,"color":"#5b8be3"},{"amount":1,"color":"#968bf9"},{"amount":1,"color":"#fae3bd"},{"amount":1,"color":"#3ff5c2"},{"amount":1,"color":"#a7faa0"},{"amount":1,"color":"#acf5e6"},{"amount":1,"color":"#59ed69"},{"amount":1,"color":"#54f4a0"},{"amount":1,"color":"#528de6"},{"amount":1,"color":"#f77ba7"},{"amount":1,"color":"#fea8c2"},{"amount":1,"color":"#fce9a6"},{"amount":1,"color":"#f15aee"},{"amount":1,"color":"#f3615f"},{"amount":1,"color":"#d8f476"},{"amount":1,"color":"#83f5be"},{"amount":1,"color":"#acf153"},{"amount":1,"color":"#fcceef"},{"amount":1,"color":"#fbaa49"},{"amount":1,"color":"#faaf92"},{"amount":1,"color":"#f89cbc"},{"amount":1,"color":"#a4a5f0"},{"amount":1,"color":"#f6e56d"},{"amount":1,"color":"#c8c8fd"},{"amount":1,"color":"#a6e757"},{"amount":1,"color":"#d7fab9"},{"amount":1,"color":"#98daf4"},{"amount":1,"color":"#f5cbf7"}]